coolbox/__init__.py
coolbox/__main__.py
coolbox/api.py
coolbox/cli.py
coolbox/core/__init__.py
coolbox/core/feature.py
coolbox/core/browser/__init__.py
coolbox/core/browser/base.py
coolbox/core/browser/widgets/__init__.py
coolbox/core/browser/widgets/base.py
coolbox/core/browser/widgets/full.py
coolbox/core/browser/widgets/navigation.py
coolbox/core/browser/widgets/simple.py
coolbox/core/coverage/__init__.py
coolbox/core/coverage/base.py
coolbox/core/coverage/highlights.py
coolbox/core/coverage/hlines.py
coolbox/core/coverage/vlines.py
coolbox/core/frame/__init__.py
coolbox/core/frame/base.py
coolbox/core/frame/frame.py
coolbox/core/frame/superframe/__init__.py
coolbox/core/frame/superframe/base.py
coolbox/core/frame/superframe/jointview.py
coolbox/core/track/__init__.py
coolbox/core/track/bam.py
coolbox/core/track/base.py
coolbox/core/track/gtf.py
coolbox/core/track/ideogram.py
coolbox/core/track/pseudo.py
coolbox/core/track/tad.py
coolbox/core/track/arcs/__init__.py
coolbox/core/track/arcs/base.py
coolbox/core/track/arcs/bedpe.py
coolbox/core/track/arcs/hicpeaks.py
coolbox/core/track/arcs/pairs.py
coolbox/core/track/arcs/plot.py
coolbox/core/track/bed/__init__.py
coolbox/core/track/bed/base.py
coolbox/core/track/bed/bed.py
coolbox/core/track/bed/plot.py
coolbox/core/track/hicmat/__init__.py
coolbox/core/track/hicmat/base.py
coolbox/core/track/hicmat/cool.py
coolbox/core/track/hicmat/dothic.py
coolbox/core/track/hicmat/hicmat.py
coolbox/core/track/hicmat/plot.py
coolbox/core/track/hicmat/process.py
coolbox/core/track/hicmat/hicdiff/__init__.py
coolbox/core/track/hicmat/hicdiff/diff.py
coolbox/core/track/hicmat/hicdiff/selfish.py
coolbox/core/track/hist/__init__.py
coolbox/core/track/hist/bam.py
coolbox/core/track/hist/base.py
coolbox/core/track/hist/bedgraph.py
coolbox/core/track/hist/bigwig.py
coolbox/core/track/hist/hicfeature.py
coolbox/core/track/hist/plot.py
coolbox/core/track/hist/snp.py
coolbox/genome/hg19.txt
coolbox/genome/hg38.txt
coolbox/genome/mm10.txt
coolbox-0.4.0.dist-info/licenses/LICENSE
coolbox-0.4.0.dist-info/METADATA
coolbox-0.4.0.dist-info/WHEEL
coolbox-0.4.0.dist-info/entry_points.txt
coolbox-0.4.0.dist-info/top_level.txt
coolbox-0.4.0.dist-info/RECORD
