Metadata-Version: 2.4
Name: coolbox
Version: 0.4.0
Summary: Jupyter notebook based genomic data visulization toolkit.
Author-email: Weize Xu <vet.xwz@gmail.com>
License: GPLv3
Project-URL: Homepage, https://github.com/GangCaoLab/CoolBox
Project-URL: Documentation, https://gangcaolab.github.io/CoolBox/index.html
Project-URL: Repository, https://github.com/GangCaoLab/CoolBox
Project-URL: Bug Tracker, https://github.com/GangCaoLab/CoolBox/issues
Keywords: genomics,bioinformatics,visualization,Jupyter
Classifier: Development Status :: 3 - Alpha
Classifier: Operating System :: POSIX
Classifier: Programming Language :: Python
Classifier: Programming Language :: Python :: 3
Classifier: Programming Language :: Python :: 3.9
Classifier: Programming Language :: Python :: 3.10
Classifier: Programming Language :: Python :: 3.11
Classifier: Programming Language :: Python :: 3.12
Classifier: License :: OSI Approved :: GNU General Public License v3 (GPLv3)
Classifier: Intended Audience :: Science/Research
Classifier: Topic :: Scientific/Engineering :: Bio-Informatics
Classifier: Topic :: Scientific/Engineering :: Visualization
Requires-Python: <4,>=3.7
License-File: LICENSE
Requires-Dist: scipy>=1.0.0
Requires-Dist: numpy
Requires-Dist: pandas>=1.0.0
Requires-Dist: statsmodels
Requires-Dist: matplotlib>=3.8.4
Requires-Dist: jupyter>=1.0.0
Requires-Dist: ipywidgets>=7.5.1
Requires-Dist: nbformat
Requires-Dist: voila
Requires-Dist: svgutils
Requires-Dist: intervaltree
Requires-Dist: dna_features_viewer
Requires-Dist: h5py
Requires-Dist: cooler
Requires-Dist: numpydoc
Requires-Dist: fire
Requires-Dist: oxbow>=0.4.2
Provides-Extra: doc
Requires-Dist: sphinx_rtd_theme; extra == "doc"
Requires-Dist: autodocsumm; extra == "doc"
Requires-Dist: recommonmark; extra == "doc"
Requires-Dist: nbsphinx; extra == "doc"
Requires-Dist: sphinx_gallery; extra == "doc"
Requires-Dist: sphinx-autobuild; extra == "doc"
Provides-Extra: strawc
Requires-Dist: strawC; extra == "strawc"
Provides-Extra: dev
Requires-Dist: pytest; extra == "dev"
Requires-Dist: pytest-cov; extra == "dev"
Requires-Dist: build; extra == "dev"
Dynamic: license-file
